{
    "@class": "com.kony.gen.viz.model.component.KVizLabel",
    "DNDConfig": null,
    "__parentReadjusting__": false,
    "_height_": {
        "type": "string",
        "value": "100%"
    },
    "_left_": {
        "type": "string",
        "value": "301px"
    },
    "_margin_": [
        0,
        0,
        0,
        0
    ],
    "_padding_": [
        2,
        0,
        0,
        0
    ],
    "_right_": {
        "type": "string",
        "value": "0px"
    },
    "_skin_": "sf7786d3c48747e7a9fae835bcd45255",
    "_text_": "Work Number",
    "_top_": {
        "type": "number",
        "value": ""
    },
    "_width_": {
        "type": "number",
        "value": ""
    },
    "_wrapping_": 2,
    "android": {
        "textStyle": {
            "letterSpacing": "0",
            "lineSpacing": 0,
            "strikeThrough": false
        }
    },
    "canUpdateUI": true,
    "centery": {
        "type": "string",
        "value": "50%"
    },
    "containerweight": 100,
    "contentalignment": 4,
    "focusskin": "psd18dbed16e4011e8bfbd290fbe0bfa7d",
    "id": "lblWorkNumberValue",
    "info": null,
    "ipad": {
        "psp": {
            "wrapping": 2
        },
        "textStyle": {
            "baseline": 0,
            "letterSpacing": "0",
            "lineSpacing": 0,
            "strikeThrough": false
        }
    },
    "iphone": {
        "psp": {
            "wrapping": 2
        },
        "textStyle": {
            "baseline": 0,
            "letterSpacing": "0",
            "lineSpacing": 0,
            "strikeThrough": false
        }
    },
    "isvisible": true,
    "kuid": "a4f278e84da4490d9d22c3460a45b63f",
    "name": "kony.ui.Label",
    "paddinginpixel": false,
    "parent": "flxWorkNumber",
    "pf": "frmEmpDetails",
    "responsiveData": {
        "b5": {
            "centerY": {
                "type": "string",
                "value": ""
            },
            "height": {
                "type": "string",
                "value": "50px"
            },
            "left": {
                "type": "string",
                "value": "0px"
            },
            "padding": [
                2,
                0,
                0,
                0
            ],
            "skin": "s87faf2e150f48aaaa970200f2f23b7b",
            "top": {
                "type": "string",
                "value": "0px"
            },
            "width": {
                "type": "string",
                "value": "100%"
            }
        }
    },
    "tooltip": "",
    "wType": "Label",
    "zindex": 20
}