{
    "AS_ListBox_ef22aeca46fd4539bb75703f85233c42": {
        "id": "AS_ListBox_ef22aeca46fd4539bb75703f85233c42",
        "type": "ACTION_SEQUENCE",
        "params": [{
            "datatype": "collection",
            "name": "eventobject"
        }],
        "contextObj": {
            "name": "frmSetting",
            "type": "forms",
            "platform": "",
            "KUID": "a369de5a326c43e0b764ef2eef239f51"
        },
        "language": "js",
        "actions": [{
            "id": "INVOKE_FUNCTION___j4bd2eea56cc4282b5434effe7b7b2a2",
            "type": "INVOKE_FUNCTION",
            "sequenceKUID": "onMasterDataSelected",
            "display": "onMasterDataSelected",
            "inputparams": [{
                "name": "param",
                "value": " eventobject"
            }, {
                "name": "param2",
                "value": ""
            }],
            "parentId": null,
            "callbackType": null,
            "disabled": null,
            "source": "controller"
        }]
    }
}